openweatherappapi/01d@2x.png
openweatherappapi/01n@2x.png
openweatherappapi/02d@2x.png
openweatherappapi/02n@2x.png
openweatherappapi/03d@2x.png
openweatherappapi/03n@2x.png
openweatherappapi/04d@2x.png
openweatherappapi/04n@2x.png
openweatherappapi/09d@2x.png
openweatherappapi/09n@2x.png
openweatherappapi/10d@2x.png
openweatherappapi/10n@2x.png
openweatherappapi/11d@2x.png
openweatherappapi/11n@2x.png
openweatherappapi/13d@2x.png
openweatherappapi/13n@2x.png
openweatherappapi/50d@2x.png
openweatherappapi/50n@2x.png
openweatherappapi/Layer 6.png
openweatherappapi/Layer 7.png
openweatherappapi/Readme.md
openweatherappapi/Rounded Rectangle 1.png
openweatherappapi/Rounded Rectangle 2 copy.png
openweatherappapi/Rounded Rectangle 2.png
openweatherappapi/Rounded Rectangle 3.png
openweatherappapi/__init__.py
openweatherappapi/logo.png
openweatherappapi/__pycache__/__init__.cpython-311.pyc
openweatherappapi-8.0.0.dist-info/METADATA
openweatherappapi-8.0.0.dist-info/WHEEL
openweatherappapi-8.0.0.dist-info/top_level.txt
openweatherappapi-8.0.0.dist-info/RECORD
