Metadata-Version: 2.1
Name: openweatherappapi
Version: 8.0.0
Summary: Weather App
Home-page: https://github.com/alikushbaev/Weatherapp
Author: __token__
Author-email: alikushbaev2@gmail.com
Project-URL: Documentation, https://github.com/alikushbaev/Weatherapp
Classifier: Programming Language :: Python :: 3
Classifier: License :: OSI Approved :: MIT License
Classifier: Operating System :: OS Independent
Requires-Python: >=3.11
Requires-Dist: geopy
Requires-Dist: pystray
Requires-Dist: datetime
Requires-Dist: pytz
Requires-Dist: requests
Requires-Dist: timezonefinder
Requires-Dist: pillow
